topsis/__init__.py
topsis/__main__.py
Topsis_Shanya_101953017-1.0.0.dist-info/LICENSE
Topsis_Shanya_101953017-1.0.0.dist-info/METADATA
Topsis_Shanya_101953017-1.0.0.dist-info/WHEEL
Topsis_Shanya_101953017-1.0.0.dist-info/entry_points.txt
Topsis_Shanya_101953017-1.0.0.dist-info/top_level.txt
Topsis_Shanya_101953017-1.0.0.dist-info/RECORD
