Metadata-Version: 2.1
Name: Topsis-Shanya-101953017
Version: 1.0.0
Summary: It performs topsis for any model
Home-page: https://github.com/Shanya1356/Topsis-Shanya-101953017
Author: Shanya
Author-email: sbibhuty_be19@thapar.edu
License: MIT
Platform: UNKNOWN
Classifier: License :: OSI Approved :: MIT License
Classifier: Programming Language :: Python :: 3.6
Classifier: Programming Language :: Python :: 3.7
Classifier: Programming Language :: Python :: 3.8
License-File: LICENSE
